LICENSE
MANIFEST.in
README.md
requirements.txt
setup.cfg
setup.py
moippy/__init__.py
moippy.egg-info/PKG-INFO
moippy.egg-info/SOURCES.txt
moippy.egg-info/dependency_links.txt
moippy.egg-info/requires.txt
moippy.egg-info/top_level.txt
moippy/entities/__init__.py
moippy/entities/address.py
moippy/entities/amount.py
moippy/entities/app.py
moippy/entities/bankaccount.py
moippy/entities/boleto.py
moippy/entities/cancellationdetails.py
moippy/entities/checkoutpreference.py
moippy/entities/creditcard.py
moippy/entities/customer.py
moippy/entities/device.py
moippy/entities/email.py
moippy/entities/entrie.py
moippy/entities/escrow.py
moippy/entities/event.py
moippy/entities/fee.py
moippy/entities/fundinginstrument.py
moippy/entities/geolocation.py
moippy/entities/holder.py
moippy/entities/identitydocument.py
moippy/entities/installment.py
moippy/entities/instructionline.py
moippy/entities/moipaccount.py
moippy/entities/onlinebankdebit.py
moippy/entities/order.py
moippy/entities/orderitem.py
moippy/entities/payment.py
moippy/entities/person.py
moippy/entities/phone.py
moippy/entities/receiver.py
moippy/entities/redirecturl.py
moippy/entities/reference.py
moippy/entities/refund.py
moippy/entities/statement.py
moippy/entities/subtotal.py
moippy/entities/taxdocument.py
moippy/entities/transfer.py
moippy/entities/transferinstrument.py
moippy/entities/webhook.py
moippy/entities/webhookpreference.py
moippy/entities/lib/__init__.py
moippy/entities/lib/datatype.py
moippy/entities/lib/entity.py
moippy/services/__init__.py
moippy/services/balance.py
moippy/services/bankaccounts.py
moippy/services/creditcard.py
moippy/services/customer.py
moippy/services/extrato.py
moippy/services/order.py
moippy/services/refunds.py
moippy/services/statements.py
moippy/services/webhooks.py
moippy/utils/__init__.py
moippy/utils/constants.py
moippy/utils/moip.py
moippy/utils/validate_webhook.py
test/test.py